hfutils/__init__.py
hfutils/__main__.py
hfutils/archive/__init__.py
hfutils/archive/base.py
hfutils/archive/rar.py
hfutils/archive/sevenz.py
hfutils/archive/tar.py
hfutils/archive/zip.py
hfutils/cache/__init__.py
hfutils/cache/delete.py
hfutils/config/__init__.py
hfutils/config/meta.py
hfutils/entry/__init__.py
hfutils/entry/base.py
hfutils/entry/cli.py
hfutils/entry/clone.py
hfutils/entry/dispatch.py
hfutils/entry/download.py
hfutils/entry/duplicate.py
hfutils/entry/ils.py
hfutils/entry/index.py
hfutils/entry/ls.py
hfutils/entry/ls_repo.py
hfutils/entry/rollback.py
hfutils/entry/squash.py
hfutils/entry/tree.py
hfutils/entry/upload.py
hfutils/entry/warmup.py
hfutils/entry/whoami.py
hfutils/index/__init__.py
hfutils/index/fetch.py
hfutils/index/hash.py
hfutils/index/local_fetch.py
hfutils/index/make.py
hfutils/index/validate.py
hfutils/meta/__init__.py
hfutils/meta/version.py
hfutils/operate/__init__.py
hfutils/operate/base.py
hfutils/operate/download.py
hfutils/operate/duplicate.py
hfutils/operate/upload.py
hfutils/operate/validate.py
hfutils/operate/warmup.py
hfutils/repository/__init__.py
hfutils/repository/base.py
hfutils/repository/clone.py
hfutils/repository/rollback.py
hfutils/repository/size.py
hfutils/repository/url.py
hfutils/utils/__init__.py
hfutils/utils/archive.py
hfutils/utils/arrange.py
hfutils/utils/binary.py
hfutils/utils/binary_proxy.py
hfutils/utils/data.py
hfutils/utils/download.py
hfutils/utils/ext.py
hfutils/utils/heap.py
hfutils/utils/irregular_repo.json
hfutils/utils/logging.py
hfutils/utils/model.py
hfutils/utils/number.py
hfutils/utils/path.py
hfutils/utils/session.py
hfutils/utils/temp.py
hfutils/utils/tqdm_.py
hfutils/utils/type_.py
hfutils/utils/version.py
hfutils/utils/walk.py
hfutils-0.13.0.dist-info/LICENSE
hfutils-0.13.0.dist-info/METADATA
hfutils-0.13.0.dist-info/WHEEL
hfutils-0.13.0.dist-info/entry_points.txt
hfutils-0.13.0.dist-info/top_level.txt
hfutils-0.13.0.dist-info/RECORD
