Metadata-Version: 2.1
Name: hfutils
Version: 0.13.0
Summary: Useful utilities for huggingface
Home-page: https://github.com/deepghs/hfutils
Author: narugo1992
Author-email: narugo1992@deepghs.org
License: Apache License, Version 2.0
Project-URL: Bug Reports, https://github.com/deepghs/hfutils/issues
Project-URL: Source, https://github.com/deepghs/hfutils
Project-URL: Documentation, https://hfutils.deepghs.org/
Keywords: huggingface,download,upload,batch processing,data processing,machine learning,ai
Classifier: Development Status :: 5 - Production/Stable
Classifier: Intended Audience :: Developers
Classifier: Intended Audience :: Science/Research
Classifier: Intended Audience :: Information Technology
Classifier: License :: OSI Approved :: MIT License
Classifier: Programming Language :: Python
Classifier: Programming Language :: Python :: 3
Classifier: Programming Language :: Python :: 3 :: Only
Classifier: Programming Language :: Python :: 3.8
Classifier: Programming Language :: Python :: 3.9
Classifier: Programming Language :: Python :: 3.10
Classifier: Programming Language :: Python :: 3.11
Classifier: Programming Language :: Python :: 3.12
Classifier: Programming Language :: Python :: 3.13
Classifier: Operating System :: OS Independent
Classifier: Operating System :: POSIX
Classifier: Operating System :: Microsoft :: Windows
Classifier: Operating System :: MacOS
Classifier: Topic :: Scientific/Engineering
Classifier: Topic :: Scientific/Engineering :: Artificial Intelligence
Classifier: Topic :: Software Development :: Libraries
Classifier: Topic :: Software Development :: Libraries :: Python Modules
Classifier: Topic :: Internet :: File Transfer Protocol (FTP)
Classifier: Topic :: Utilities
Classifier: Typing :: Typed
Classifier: Natural Language :: English
Requires-Python: >=3.8
License-File: LICENSE
Requires-Dist: hbutils >=0.10.1
Requires-Dist: huggingface-hub >=0.31.0
Requires-Dist: tqdm
Requires-Dist: requests
Requires-Dist: click >=7
Requires-Dist: tzlocal
Requires-Dist: natsort
Requires-Dist: urlobject
Requires-Dist: random-user-agent
Requires-Dist: cachetools
Requires-Dist: wcmatch >=10
Provides-Extra: 7z
Requires-Dist: py7zr ; extra == '7z'
Requires-Dist: fsspec <=2025.3.0,>=2024 ; python_version <= "3.8"
Requires-Dist: fsspec >=2024 ; python_version > "3.8"
Provides-Extra: build
Requires-Dist: pyinstaller <5,>=4.7 ; extra == 'build'
Requires-Dist: setuptools <70 ; extra == 'build'
Requires-Dist: hbutils >=0.10.0 ; extra == 'build'
Provides-Extra: doc
Requires-Dist: Jinja2 >=3.0.0 ; extra == 'doc'
Requires-Dist: sphinx >=3.2.0 ; extra == 'doc'
Requires-Dist: sphinx-rtd-theme >=0.4.3 ; extra == 'doc'
Requires-Dist: enum-tools >=0.9.0 ; extra == 'doc'
Requires-Dist: sphinx-toolbox ; extra == 'doc'
Requires-Dist: plantumlcli >=0.0.2 ; extra == 'doc'
Requires-Dist: packaging ; extra == 'doc'
Requires-Dist: sphinx-multiversion >=0.2.4 ; extra == 'doc'
Requires-Dist: where >=1.0.2 ; extra == 'doc'
Requires-Dist: easydict <2,>=1.7 ; extra == 'doc'
Requires-Dist: responses >=0.20.0 ; extra == 'doc'
Requires-Dist: natsort ; extra == 'doc'
Requires-Dist: nbsphinx >=0.8.8 ; extra == 'doc'
Requires-Dist: ipython >=7.16.3 ; extra == 'doc'
Requires-Dist: psutil >=5.8.0 ; extra == 'doc'
Requires-Dist: ipykernel >=6.15 ; extra == 'doc'
Requires-Dist: py-cpuinfo >=8.0.0 ; extra == 'doc'
Requires-Dist: click >=7.0.0 ; extra == 'doc'
Requires-Dist: pandas ; extra == 'doc'
Provides-Extra: rar
Requires-Dist: rarfile ; extra == 'rar'
Provides-Extra: test
Requires-Dist: coverage >=5 ; extra == 'test'
Requires-Dist: mock >=4.0.3 ; extra == 'test'
Requires-Dist: flake8 ~=3.5 ; extra == 'test'
Requires-Dist: testfixtures >=6.18.5 ; extra == 'test'
Requires-Dist: pytest ~=6.2.5 ; extra == 'test'
Requires-Dist: pytest-cov ~=3.0.0 ; extra == 'test'
Requires-Dist: pytest-mock ~=3.6.1 ; extra == 'test'
Requires-Dist: pytest-xdist >=1.34.0 ; extra == 'test'
Requires-Dist: pytest-rerunfailures ~=10.2 ; extra == 'test'
Requires-Dist: pytest-timeout ~=2.0.2 ; extra == 'test'
Requires-Dist: pytest-benchmark ~=3.4.0 ; extra == 'test'
Requires-Dist: easydict <2,>=1.7 ; extra == 'test'
Requires-Dist: testtools >=2 ; extra == 'test'
Requires-Dist: where >=1.0.2 ; extra == 'test'
Requires-Dist: responses >=0.20.0 ; extra == 'test'
Requires-Dist: natsort ; extra == 'test'
Provides-Extra: transfer
Requires-Dist: hf-transfer ; extra == 'transfer'
